adaptive_scheduler/__init__.py
adaptive_scheduler/_executor.py
adaptive_scheduler/_mock_scheduler.py
adaptive_scheduler/_version.py
adaptive_scheduler/client_support.py
adaptive_scheduler/scheduler.py
adaptive_scheduler/server_support.py
adaptive_scheduler/utils.py
adaptive_scheduler/widgets.py
adaptive_scheduler/_scheduler/__init__.py
adaptive_scheduler/_scheduler/base_scheduler.py
adaptive_scheduler/_scheduler/common.py
adaptive_scheduler/_scheduler/local.py
adaptive_scheduler/_scheduler/pbs.py
adaptive_scheduler/_scheduler/slurm.py
adaptive_scheduler/_server_support/__init__.py
adaptive_scheduler/_server_support/base_manager.py
adaptive_scheduler/_server_support/common.py
adaptive_scheduler/_server_support/database_manager.py
adaptive_scheduler/_server_support/job_manager.py
adaptive_scheduler/_server_support/kill_manager.py
adaptive_scheduler/_server_support/launcher.py
adaptive_scheduler/_server_support/multi_run_manager.py
adaptive_scheduler/_server_support/parse_logs.py
adaptive_scheduler/_server_support/run_manager.py
adaptive_scheduler/_server_support/slurm_run.py
adaptive_scheduler-2.16.0.dist-info/licenses/AUTHORS.md
adaptive_scheduler-2.16.0.dist-info/licenses/LICENSE
adaptive_scheduler-2.16.0.dist-info/METADATA
adaptive_scheduler-2.16.0.dist-info/WHEEL
adaptive_scheduler-2.16.0.dist-info/entry_points.txt
adaptive_scheduler-2.16.0.dist-info/top_level.txt
adaptive_scheduler-2.16.0.dist-info/RECORD
